{"/a-really-long-hebrew/permalink/":"https://polyglot.untra.io/um-longo/permalink/","/eine-wirklich-lange/permalink/":"https://polyglot.untra.io/um-longo/permalink/","/a-really-long/permalink/":"https://polyglot.untra.io/um-longo/permalink/","/una-muy-larga/permalink/":"https://polyglot.untra.io/um-longo/permalink/","/un-tres-long/permalink/":"https://polyglot.untra.io/um-longo/permalink/","/a-really-long-korean/permalink/":"https://polyglot.untra.io/um-longo/permalink/","/een-hele-lange/permalink/":"https://polyglot.untra.io/um-longo/permalink/","/a-really-long-russian/permalink/":"https://polyglot.untra.io/um-longo/permalink/","/a-really-long-chinese/permalink/":"https://polyglot.untra.io/um-longo/permalink/"}